moderatelyai_sdk-0.2.7.dist-info/METADATA
moderatelyai_sdk-0.2.7.dist-info/WHEEL
moderatelyai_sdk-0.2.7.dist-info/entry_points.txt
moderatelyai_sdk/__init__.py
moderatelyai_sdk/_base_client.py
moderatelyai_sdk/_base_client_async.py
moderatelyai_sdk/client.py
moderatelyai_sdk/client_async.py
moderatelyai_sdk/exceptions.py
moderatelyai_sdk/models/__init__.py
moderatelyai_sdk/models/_base.py
moderatelyai_sdk/models/_base_async.py
moderatelyai_sdk/models/_shared/__init__.py
moderatelyai_sdk/models/_shared/dataset_operations.py
moderatelyai_sdk/models/dataset.py
moderatelyai_sdk/models/dataset_async.py
moderatelyai_sdk/models/dataset_schema_version.py
moderatelyai_sdk/models/dataset_schema_version_async.py
moderatelyai_sdk/models/file.py
moderatelyai_sdk/models/file_async.py
moderatelyai_sdk/models/pipeline.py
moderatelyai_sdk/models/pipeline_async.py
moderatelyai_sdk/models/pipeline_configuration_version.py
moderatelyai_sdk/models/pipeline_configuration_version_async.py
moderatelyai_sdk/models/pipeline_execution.py
moderatelyai_sdk/models/pipeline_execution_async.py
moderatelyai_sdk/models/user.py
moderatelyai_sdk/models/user_async.py
moderatelyai_sdk/resources/__init__.py
moderatelyai_sdk/resources/_base.py
moderatelyai_sdk/resources/agent_executions.py
moderatelyai_sdk/resources/agents.py
moderatelyai_sdk/resources/dataset_schema_versions.py
moderatelyai_sdk/resources/datasets.py
moderatelyai_sdk/resources/files.py
moderatelyai_sdk/resources/pipeline_configuration_versions.py
moderatelyai_sdk/resources/pipeline_executions.py
moderatelyai_sdk/resources/pipelines.py
moderatelyai_sdk/resources/teams.py
moderatelyai_sdk/resources/users.py
moderatelyai_sdk/resources_async/__init__.py
moderatelyai_sdk/resources_async/_base.py
moderatelyai_sdk/resources_async/agent_executions.py
moderatelyai_sdk/resources_async/agents.py
moderatelyai_sdk/resources_async/dataset_schema_versions.py
moderatelyai_sdk/resources_async/datasets.py
moderatelyai_sdk/resources_async/files.py
moderatelyai_sdk/resources_async/pipeline_configuration_versions.py
moderatelyai_sdk/resources_async/pipeline_executions.py
moderatelyai_sdk-0.2.7.dist-info/RECORD
