Metadata-Version: 2.1
Name: moderatelyai-sdk
Version: 0.2.7
Summary: Python SDK for Moderately AI platform
Keywords: ai,sdk,api,moderately
Author-Email: Moderately AI <sdk@moderately.ai>
License: MIT
Classifier: Development Status :: 3 - Alpha
Classifier: Intended Audience :: Developers
Classifier: License :: OSI Approved :: MIT License
Classifier: Programming Language :: Python :: 3
Classifier: Programming Language :: Python :: 3.8
Classifier: Programming Language :: Python :: 3.9
Classifier: Programming Language :: Python :: 3.10
Classifier: Programming Language :: Python :: 3.11
Classifier: Programming Language :: Python :: 3.12
Classifier: Topic :: Software Development :: Libraries :: Python Modules
Project-URL: Homepage, https://github.com/moderately-ai/platform-sdk
Project-URL: Documentation, https://moderately-ai-platform-sdk.readthedocs.io/
Project-URL: Repository, https://github.com/moderately-ai/platform-sdk
Project-URL: Issues, https://github.com/moderately-ai/platform-sdk/issues
Requires-Python: >=3.8
Requires-Dist: httpx>=0.24.0
Requires-Dist: pydantic>=1.10.0
Requires-Dist: typing-extensions>=4.0.0
Requires-Dist: aiofiles>=23.0.0
